processamento_de_imagem/__init__.py
processamento_de_imagem/processamento/__init__.py
processamento_de_imagem/processamento/combinacao.py
processamento_de_imagem/processamento/transformacao.py
processamento_de_imagem/utilidades/__init__.py
processamento_de_imagem/utilidades/io.py
processamento_de_imagem/utilidades/plot.py
processamento_de_imagem-0.0.2.dist-info/METADATA
processamento_de_imagem-0.0.2.dist-info/WHEEL
processamento_de_imagem-0.0.2.dist-info/top_level.txt
processamento_de_imagem-0.0.2.dist-info/RECORD
