Metadata-Version: 2.1
Name: processamento-de-imagem
Version: 0.0.2
Summary: Processamento de imagem usando combinação de histograma
Home-page: https://github.com/Jhonathanalvesbr/processamento-de-imagem
Author: Jhonathan Alves
License: UNKNOWN
Platform: UNKNOWN
Requires-Python: >=3.5
